{"description":"Verify User has logged successfuly| Verifying the Login Page - ","passed":false,"pending":false,"os":"Windows","instanceId":6328,"browser":{"name":"chrome","version":"79.0.3945.88"},"message":["Expected 'https://archway-premiernutrition-qa.azurewebsites.net/login' to contain 'home'."],"trace":["Error: Failed expectation\n    at UserContext.<anonymous> (C:\\Users\\NareshS\\eclipse-workspace\\protrract\\PM_Byer\\specs\\LoginPage\\LoginPage_spec.js:521:18)\n    at C:\\Users\\NareshS\\AppData\\Roaming\\npm\\node_modules\\protractor\\node_modules\\jasminewd2\\index.js:112:25\n    at new ManagedPromise (C:\\Users\\NareshS\\AppData\\Roaming\\npm\\node_modules\\protractor\\node_modules\\selenium-webdriver\\lib\\promise.js:1077:7)\n    at ControlFlow.promise (C:\\Users\\NareshS\\AppData\\Roaming\\npm\\node_modules\\protractor\\node_modules\\selenium-webdriver\\lib\\promise.js:2505:12)\n    at schedulerExecute (C:\\Users\\NareshS\\AppData\\Roaming\\npm\\node_modules\\protractor\\node_modules\\jasminewd2\\index.js:95:18)\n    at TaskQueue.execute_ (C:\\Users\\NareshS\\AppData\\Roaming\\npm\\node_modules\\protractor\\node_modules\\selenium-webdriver\\lib\\promise.js:3084:14)\n    at TaskQueue.executeNext_ (C:\\Users\\NareshS\\AppData\\Roaming\\npm\\node_modules\\protractor\\node_modules\\selenium-webdriver\\lib\\promise.js:3067:27)\n    at C:\\Users\\NareshS\\AppData\\Roaming\\npm\\node_modules\\protractor\\node_modules\\selenium-webdriver\\lib\\promise.js:2974:25\n    at C:\\Users\\NareshS\\AppData\\Roaming\\npm\\node_modules\\protractor\\node_modules\\selenium-webdriver\\lib\\promise.js:668:7"],"browserLogs":[],"screenShotFile":"007b007f-00a3-0043-00b4-00bb0010005f.png","timestamp":1577701016700,"duration":23}
